fix_busted_json.py
fix_busted_json-0.0.19.dist-info/licenses/LICENSE
fix_busted_json-0.0.19.dist-info/METADATA
fix_busted_json-0.0.19.dist-info/WHEEL
fix_busted_json-0.0.19.dist-info/top_level.txt
fix_busted_json-0.0.19.dist-info/RECORD
